CHANGES.txt
DEPENDENCES.txt
README.txt
setup.py
src/ng/__init__.py
src/ng.app.skinswitch.egg-info/PKG-INFO
src/ng.app.skinswitch.egg-info/SOURCES.txt
src/ng.app.skinswitch.egg-info/dependency_links.txt
src/ng.app.skinswitch.egg-info/namespace_packages.txt
src/ng.app.skinswitch.egg-info/not-zip-safe
src/ng.app.skinswitch.egg-info/requires.txt
src/ng.app.skinswitch.egg-info/top_level.txt
src/ng/app/__init__.py
src/ng/app/skinswitch/__init__.py
src/ng/app/skinswitch/configure.zcml
src/ng/app/skinswitch/interfaces.py
src/ng/app/skinswitch/ng.app.skinswitch.txt
src/ng/app/skinswitch/skinswitchableadapter.py
src/ng/app/skinswitch/skinswitchannotation.py
src/ng/app/skinswitch/skinswitchhandler.py
src/ng/app/skinswitch/browser/__init__.py
src/ng/app/skinswitch/browser/configure.zcml
src/ng/app/skinswitch/etc/ng.app.skinswitch-configure.zcml